MANIFEST.in
setup.py
./__init__.py
./__openerp__.py
./http.py
./session.py
./cli/__init__.py
./cli/test_js.py
./controllers/__init__.py
./controllers/main.py
./controllers/testing.py
./tests/__init__.py
./tests/test_dataset.py
./tests/test_js.py
./tests/test_menu.py
./tests/test_serving_base.py
./tests/qunitsuite/__init__.py
./tests/qunitsuite/suite.py
doc/Makefile
doc/addon-structure.txt
doc/async.rst
doc/changelog-7.0.rst
doc/client_action.rst
doc/conf.py
doc/form_view.rst
doc/guidelines.rst
doc/index.rst
doc/list_view.rst
doc/make.bat
doc/module.rst
doc/qweb.rst
doc/rpc.rst
doc/search_view.rst
doc/test-report.txt
doc/testing.rst
doc/widget.rst
doc/_static/openerp.png
doc/_templates/sidebarintro.html
doc/_templates/sidebarlogo.html
doc/_themes/LICENSE
doc/_themes/README
doc/_themes/flask_theme_support.py
doc/_themes/flask/layout.html
doc/_themes/flask/relations.html
doc/_themes/flask/theme.conf
doc/_themes/flask/static/flasky.css_t
doc/_themes/flask/static/small_flask.css
doc/_themes/flask_small/layout.html
doc/_themes/flask_small/theme.conf
doc/_themes/flask_small/static/flasky.css_t
doc/images/db-query.png
doc/images/runner.png
doc/images/runner2.png
doc/images/tests.png
doc/images/tests2.png
doc/images/tests3.png
doc/module/__init__.py
doc/module/__openerp__.py
doc/module/__openerp__.py.1.diff
doc/module/__openerp__.py.2.diff
doc/module/__openerp__.py.3.diff
doc/module/__openerp__.py.4.diff
doc/module/__openerp__.py.5.diff
doc/module/web_example.xml
doc/module/static/src/css/web_example.css
doc/module/static/src/css/web_example.css.1.diff
doc/module/static/src/js/first_module.js
doc/module/static/src/js/first_module.js.1.diff
doc/module/static/src/js/first_module.js.2.diff
doc/module/static/src/js/first_module.js.3.diff
doc/module/static/src/js/first_module.js.4.diff
doc/module/static/src/js/first_module.js.5.diff
doc/module/static/src/js/first_module.js.6.diff
doc/module/static/src/xml/web_example.xml
i18n/ar.po
i18n/bg.po
i18n/bn.po
i18n/bs.po
i18n/ca.po
openerp_web.egg-info/PKG-INFO
openerp_web.egg-info/SOURCES.txt
openerp_web.egg-info/dependency_links.txt
openerp_web.egg-info/requires.txt
openerp_web.egg-info/top_level.txt
